django_cadence/__init__.py
django_cadence/apps.py
django_cadence/apps.pyi
django_cadence/dispatcher.py
django_cadence/dispatcher.pyi
django_cadence/management/__init__.py
django_cadence/management/commands/__init__.py
django_cadence/management/commands/runcadence.py
django_cadence/scheduling.py
django_cadence/scheduling.pyi
django_cadence-0.2.0.dist-info/LICENSE.md
django_cadence-0.2.0.dist-info/WHEEL
django_cadence-0.2.0.dist-info/METADATA
django_cadence-0.2.0.dist-info/RECORD
