Metadata-Version: 2.1
Name: django-cadence
Version: 0.2.0
Summary: A package to provide periodic scheduled task support in Django
Home-page: https://github.com/LucidDan/django-cadence/
License: MPL-2.0
Keywords: scheduling,task,periodic,cron,django
Author: Dan Sloan
Author-email: dan@luciddan.com
Maintainer: Dan Sloan
Maintainer-email: dan@luciddan.com
Requires-Python: >=3.6.2,<4.0.0
Classifier: Development Status :: 2 - Pre-Alpha
Classifier: Environment :: Web Environment
Classifier: Framework :: Django :: 2.2
Classifier: Framework :: Django :: 3.0
Classifier: Framework :: Django :: 3.1
Classifier: License :: OSI Approved
Classifier: Programming Language :: Python :: 3
Classifier: Programming Language :: Python :: 3.7
Classifier: Programming Language :: Python :: 3.8
Classifier: Programming Language :: Python :: 3.9
Classifier: Typing :: Typed
Provides-Extra: celery
Provides-Extra: dramatiq
Requires-Dist: apscheduler (>=3.6.0,<4.0.0)
Requires-Dist: celery (>=4.4.0,<5.0.0); extra == "celery"
Requires-Dist: django (>=2.2.0,<3.3)
Requires-Dist: django_dramatiq (>=0.9.0,<1.0.0); extra == "dramatiq"
Project-URL: Documentation, https://django-cadence.rtfd.io/
Project-URL: Repository, https://github.com/LucidDan/django-cadence.git
Project-URL: issues, https://github.com/LucidDan/django-cadence/issues
